juq/__init__.py
juq/caller.py
juq/config.py
juq/handler/__init__.py
juq/handler/doc_handler.py
juq/handler/group_handler.py
juq/handler/repo_handler.py
juq/handler/user_handler.py
juq/misc/__init__.py
juq/misc/decorators.py
juq/misc/exceptions.py
juq/misc/request.py
juq/serializer/__init__.py
juq/serializer/book_serializer.py
juq/serializer/builder.py
juq/serializer/doc_serializer.py
juq/serializer/group_user_serializer.py
juq/serializer/user_serializer.py
juq/service/__init__.py
juq/service/config_service.py
juq/service/doc_service.py
juq/service/group_service.py
juq/service/repo_service.py
juq/service/user_service.py
juq/service/utils.py
juq/utils/__init__.py
juq/utils/md_parser.py
juq/utils/smms.py
juq-1.4.1.dist-info/LICENSE
juq-1.4.1.dist-info/METADATA
juq-1.4.1.dist-info/WHEEL
juq-1.4.1.dist-info/entry_points.txt
juq-1.4.1.dist-info/top_level.txt
juq-1.4.1.dist-info/RECORD
