Metadata-Version: 2.1
Name: juq
Version: 1.4.1
Summary: Yuque SDK and command line tool.
Home-page: https://github.com/inhzus/juq
Author: Zhi Sun
Author-email: inhzus@gmail.com
License: UNKNOWN
Platform: UNKNOWN
Classifier: Development Status :: 5 - Production/Stable
Classifier: Programming Language :: Python :: 3
Classifier: License :: OSI Approved :: MIT License
Requires-Dist: colorama (>=0.4.1)
Requires-Dist: PyYAML (>=5.1)
Requires-Dist: requests (>=2.21.0)
